hyswap/__init__.py
hyswap/_version.py
hyswap/cumulative.py
hyswap/exceedance.py
hyswap/percentiles.py
hyswap/plots.py
hyswap/rasterhydrograph.py
hyswap/runoff.py
hyswap/similarity.py
hyswap/utils.py
hyswap-1.0.0.dist-info/LICENSE.md
hyswap-1.0.0.dist-info/METADATA
hyswap-1.0.0.dist-info/WHEEL
hyswap-1.0.0.dist-info/top_level.txt
hyswap-1.0.0.dist-info/RECORD
