Metadata-Version: 2.1
Name: hyswap
Version: 1.0.0
Summary: Analysis of surface water data.
Author-email: USGS <comptools@usgs.gov>
License: License
Project-URL: homepage, https://code.usgs.gov/water/computational-tools/surface-water-work/hyswap
Project-URL: repository, https://code.usgs.gov/water/computational-tools/surface-water-work/hyswap.git
Keywords: USGS,water data,analysis
Classifier: Programming Language :: Python :: 3
Requires-Python: >=3.8
License-File: LICENSE.md
Requires-Dist: numpy
Requires-Dist: pandas
Requires-Dist: scipy
Requires-Dist: matplotlib
